ci_helper/__init__.py
ci_helper/__main__.py
ci_helper/__version__.py
ci_helper/command/__init__.py
ci_helper/command/ci_distinfo.py
ci_helper-0.3.0.dist-info/LICENSE.txt
ci_helper-0.3.0.dist-info/METADATA
ci_helper-0.3.0.dist-info/WHEEL
ci_helper-0.3.0.dist-info/entry_points.txt
ci_helper-0.3.0.dist-info/top_level.txt
ci_helper-0.3.0.dist-info/RECORD
