Metadata-Version: 2.1
Name: ci-helper
Version: 0.3.0
Summary: Get info on how a package should be built on CI
Author-email: Christopher Billington <chrisjbillington@gmail.com>
License: MIT License
Project-URL: Homepage, https://github.com/chrisjbillington/ci-helper
Project-URL: Documentation, https://github.com/chrisjbillington/ci-helper
Project-URL: Repository, https://github.com/chrisjbillington/ci-helper
Project-URL: Downloads, https://pypi.org/project/ci-helper/
Project-URL: Tracker, https://github.com/chrisjbillington/ci-helper/issues
Keywords: build,setuptools,CI
Classifier: License :: OSI Approved :: BSD License
Classifier: Programming Language :: Python :: 3 :: Only
Requires-Python: >=3.9
License-File: LICENSE.txt
Requires-Dist: setuptools
Requires-Dist: setuptools_scm
Requires-Dist: toml
Requires-Dist: requests
